norman_core/__init__.py
norman_core/_app_config.py
norman_core/clients/__init__.py
norman_core/clients/http_client.py
norman_core/clients/socket_client.py
norman_core/clients/objects/__init__.py
norman_core/clients/objects/request_encoding.py
norman_core/clients/objects/request_kwargs.py
norman_core/clients/objects/response_encoding.py
norman_core/services/__init__.py
norman_core/services/authenticate/__init__.py
norman_core/services/authenticate/login.py
norman_core/services/authenticate/register.py
norman_core/services/authenticate/signup.py
norman_core/services/file_pull/__init__.py
norman_core/services/file_pull/file_pull.py
norman_core/services/file_push/__init__.py
norman_core/services/file_push/file_push.py
norman_core/services/persist/__init__.py
norman_core/services/persist/accounts.py
norman_core/services/persist/invocation_flags.py
norman_core/services/persist/invocations.py
norman_core/services/persist/model_bases.py
norman_core/services/persist/model_flags.py
norman_core/services/persist/models.py
norman_core/services/persist/notifications.py
norman_core/services/retrieve/__init__.py
norman_core/services/retrieve/retrieve.py
norman_ml-0.1.0.dist-info/licenses/LICENSE
norman_ml-0.1.0.dist-info/METADATA
norman_ml-0.1.0.dist-info/WHEEL
norman_ml-0.1.0.dist-info/top_level.txt
norman_ml-0.1.0.dist-info/RECORD
